kdefender_wrapper/__init__.py
kdefender_wrapper/wrapper.py
kdefender_wrapper-0.2.0.dist-info/licenses/LICENSE
kdefender_wrapper-0.2.0.dist-info/METADATA
kdefender_wrapper-0.2.0.dist-info/WHEEL
kdefender_wrapper-0.2.0.dist-info/top_level.txt
kdefender_wrapper-0.2.0.dist-info/RECORD
