Metadata-Version: 2.4
Name: kdefender-wrapper
Version: 0.2.0
Summary: A Telegram bot wrapper for K-Defender security
Author-email: Fire-K <karpov.konstantin.s@gmail.com>
License-Expression: MIT
Project-URL: Homepage, https://github.com/FIRE-K/K-Defender
Project-URL: Issues, https://github.com/FIRE-K/K-Defender/issues
Classifier: Development Status :: 3 - Alpha
Classifier: Intended Audience :: Developers
Classifier: Programming Language :: Python :: 3
Classifier: Programming Language :: Python :: 3.8
Classifier: Programming Language :: Python :: 3.9
Classifier: Programming Language :: Python :: 3.10
Classifier: Programming Language :: Python :: 3.11
Classifier: Framework :: AsyncIO
Classifier: Topic :: Security
Requires-Python: >=3.8
License-File: LICENSE
Requires-Dist: telethon>=1.30.0
Dynamic: license-file
